nettrustscore-2.0.4.dist-info/licenses/LICENSE
trustpy/__init__.py
trustpy/cond_nts.py
trustpy/nts.py
nettrustscore-2.0.4.dist-info/METADATA
nettrustscore-2.0.4.dist-info/WHEEL
nettrustscore-2.0.4.dist-info/top_level.txt
nettrustscore-2.0.4.dist-info/RECORD
